{"check_worthiness": [{"check_worthiness_score": "not worth checking", "claim_type": "personal experience", "factuality_profile_source": "the_speaker", "factuality_profile_value": "CT+", "start_claim_token": ["יושב", 0, 4]}], "esp_profiles": [], "agencies": [{"source": ["חבר הכנסת פורז", 30, 44], "agency_type": "agent", "agentless_reason": null, "position": "subject", "animacy": "human", "morphology": "3sg"}], "agency_predicates": [{"source": ["עדכן", 46, 50]}], "agents_of_predicates": [{"agent_source": ["עדכן", 46, 50], "predicate_source": ["חבר הכנסת פורז", 30, 44]}], "stances": [{"confidence_level": "mid", "stance_type": "epistemic", "polarity": "positive", "reference_name": null, "reference_type": null}], "stance_polarity_indications": [], "hedges": [], "quantities": [{"expression": ["כל", 62, 64], "quantifier_type": "universal", "accuracy": null, "the_whole": null}], "named_entites": [{"entity_name": ["יושב-ראש ועדת השידורים בכנסת", 0, 28], "entity_type": "TTL"}, {"entity_name": ["ועדת השידורים", 9, 22], "entity_type": "ORG"}, {"entity_name": ["כנסת", 24, 28], "entity_type": "ORG"}, {"entity_name": ["חבר הכנסת", 30, 39], "entity_type": "TTL"}, {"entity_name": ["הכנסת", 34, 39], "entity_type": "ORG"}, {"entity_name": ["פורז", 40, 44], "entity_type": "PER"}], "this_protocol_anchors": [], "time_expression_ranges": [], "non_valid": false, "sent_text": "יושב-ראש ועדת השידורים בכנסת, חבר הכנסת פורז, עדכן אותי מחדש בכל המידע."}