{"check_worthiness": [{"check_worthiness_score": "not worth checking", "claim_type": "personal experience", "factuality_profile_source": "the_speaker", "factuality_profile_value": "CT+", "start_claim_token": ["כאשר", 0, 4]}], "esp_profiles": [], "agencies": [{"source": ["היא", 29, 32], "agency_type": "agent", "agentless_reason": null, "position": "subject", "animacy": "human", "morphology": "3sg"}], "agency_predicates": [{"source": ["להבהיר", 39, 45]}], "agents_of_predicates": [{"agent_source": ["היא", 29, 32], "predicate_source": ["להבהיר", 39, 45]}], "stances": [{"confidence_level": "mid", "stance_type": "epistemic", "polarity": "positive", "reference_name": null, "reference_type": null}], "stance_polarity_indications": [], "hedges": [], "quantities": [], "named_entites": [], "this_protocol_anchors": [], "time_expression_ranges": [], "non_valid": false, "sent_text": "כאשר היא עמדה על מהות ההצעה, היא ביקשה להבהיר זאת ברבים."}