{"check_worthiness": [{"check_worthiness_score": "not a factual proposition", "claim_type": "not a claim", "factuality_profile_source": "the_speaker", "factuality_profile_value": "Uu", "start_claim_token": ["אני", 0, 3]}, {"check_worthiness_score": "not worth checking", "claim_type": "personal experience", "factuality_profile_source": "the_speaker", "factuality_profile_value": "CT+", "start_claim_token": ["שאיסור", 32, 38]}], "esp_profiles": [{"esp": ["לומר", 9, 13], "esp_type": "NSIP"}], "agencies": [{"source": ["אני", 0, 3], "agency_type": "agent", "agentless_reason": null, "position": "subject", "animacy": "human", "morphology": "1sg"}, {"source": null, "agency_type": "agent-less", "agentless_reason": "nominal sentence", "position": null, "animacy": null, "morphology": null}], "agency_predicates": [{"source": ["לומר", 9, 13]}], "agents_of_predicates": [{"agent_source": ["לומר", 9, 13], "predicate_source": ["אני", 0, 3]}], "stances": [{"confidence_level": "irrelevant", "stance_type": "effective", "polarity": "positive", "reference_name": null, "reference_type": null}, {"confidence_level": "mid", "stance_type": "effective", "polarity": "positive", "reference_name": null, "reference_type": null}], "stance_polarity_indications": [], "hedges": [], "quantities": [{"expression": ["מחצית", 102, 107], "quantifier_type": "partial", "accuracy": null, "the_whole": null}, {"expression": ["מחצית", 135, 140], "quantifier_type": "partial", "accuracy": null, "the_whole": null}], "named_entites": [], "this_protocol_anchors": [], "time_expression_ranges": [], "non_valid": false, "sent_text": "אני רוצה לומר, אדוני היושב-ראש, שאיסור שירת חיילות, בהיותן נשים, ליד הכותל, דומה בעיני למעשה פסילה של מחצית העם היהודי, כלומר פסילה של מחצית העם היהודי במקום המקודש ביותר לעם היהודי."}