{"check_worthiness": [{"check_worthiness_score": "worth checking", "claim_type": "other type of claim", "factuality_profile_source": "the_speaker", "factuality_profile_value": "CT+", "start_claim_token": ["במועד", 35, 40]}], "esp_profiles": [], "agencies": [{"source": ["ממשלת ליטא", 91, 101], "agency_type": "agent", "agentless_reason": null, "position": "subject", "animacy": "inanimate", "morphology": "3sg"}], "agency_predicates": [{"source": ["החליטה", 84, 90]}], "agents_of_predicates": [{"agent_source": ["החליטה", 84, 90], "predicate_source": ["ממשלת ליטא", 91, 101]}], "stances": [{"confidence_level": "mid", "stance_type": "epistemic", "polarity": "positive", "reference_name": null, "reference_type": null}], "stance_polarity_indications": [], "hedges": [], "quantities": [], "named_entites": [{"entity_name": ["הכנסת", 28, 33], "entity_type": "ORG"}, {"entity_name": ["עשרת ימי תשובה", 68, 82], "entity_type": "EVE"}, {"entity_name": ["ליטא", 97, 101], "entity_type": "GPE"}, {"entity_name": ["שואה", 170, 174], "entity_type": "EVE"}], "this_protocol_anchors": [], "time_expression_ranges": [], "non_valid": false, "sent_text": "אדוני היושב-ראש, רבותי חברי הכנסת, במועד חשוב לעם היהודי, מועד החל בעשרת ימי תשובה, החליטה ממשלת ליטא לקיים דיון בפורום בין-לאומי בנושא: השבת הרכוש שנבזז מהיהודים שנספו בשואה."}