{"check_worthiness": [{"check_worthiness_score": "worth checking", "claim_type": "other type of claim", "factuality_profile_source": "the_speaker", "factuality_profile_value": "CT+", "start_claim_token": ["לפני", 0, 4]}], "esp_profiles": [], "agencies": [{"source": ["ועדת הכספים", 10, 21], "agency_type": "agent", "agentless_reason": null, "position": "subject", "animacy": "inanimate", "morphology": "3sg"}], "agency_predicates": [{"source": ["אישרה", 22, 27]}], "agents_of_predicates": [{"agent_source": ["ועדת הכספים", 10, 21], "predicate_source": ["אישרה", 22, 27]}], "stances": [{"confidence_level": "mid", "stance_type": "epistemic", "polarity": "positive", "reference_name": null, "reference_type": null}], "stance_polarity_indications": [], "hedges": [], "quantities": [{"expression": ["20 מיליון", 34, 43], "quantifier_type": "quantity_expression", "accuracy": "accurate", "the_whole": null}], "named_entites": [{"entity_name": ["ועדת הכספים", 10, 21], "entity_type": "ORG"}], "this_protocol_anchors": [], "time_expression_ranges": [{"original_time_tokens": ["לפני חודש", 0, 9], "formatted_begin_date": "to_be_added-None-None None:None", "formatted_end_date": "None-to_be_added-None None:None"}], "non_valid": false, "sent_text": "לפני חודש ועדת הכספים אישרה העברת 20 מיליון שקל לרזרבה."}