{"check_worthiness": [{"check_worthiness_score": "not worth checking", "claim_type": "prediction", "factuality_profile_source": "the_speaker", "factuality_profile_value": "CT+", "start_claim_token": ["כל", 0, 2]}], "esp_profiles": [], "agencies": [{"source": ["כל מה שתשלום הביטוח הלאומי עליו הוא לפי המס השולי", 0, 49], "agency_type": "experiencer", "agentless_reason": null, "position": "subject", "animacy": "inanimate", "morphology": "3sg"}], "agency_predicates": [{"source": ["ימשיך", 51, 56]}], "agents_of_predicates": [{"agent_source": ["ימשיך", 51, 56], "predicate_source": ["כל מה שתשלום הביטוח הלאומי עליו הוא לפי המס השולי", 0, 49]}], "stances": [{"confidence_level": "mid", "stance_type": "epistemic", "polarity": "positive", "reference_name": null, "reference_type": null}], "stance_polarity_indications": [], "hedges": [], "quantities": [{"expression": ["כל", 0, 2], "quantifier_type": "universal", "accuracy": null, "the_whole": null}, {"expression": ["12", 92, 94], "quantifier_type": "quantity_expression", "accuracy": "accurate", "the_whole": null}, {"expression": ["7", 104, 105], "quantifier_type": "quantity_expression", "accuracy": "accurate", "the_whole": null}, {"expression": ["5", 130, 131], "quantifier_type": "quantity_expression", "accuracy": "accurate", "the_whole": null}], "named_entites": [{"entity_name": ["הביטוח הלאומי", 13, 26], "entity_type": "ORG"}], "this_protocol_anchors": [], "time_expression_ranges": [], "non_valid": false, "sent_text": "כל מה שתשלום הביטוח הלאומי עליו הוא לפי המס השולי, ימשיך ויהיה מחויב בביטוח לאומי בשיעור של 12 אחוזים – 7 אחוזים ביטוח לאומי ועוד 5 אחוזים מס בריאות."}