{"check_worthiness": [{"check_worthiness_score": "not worth checking", "claim_type": "personal experience", "factuality_profile_source": "the_speaker", "factuality_profile_value": "Uu", "start_claim_token": ["אני", 0, 3]}], "esp_profiles": [], "agencies": [{"source": ["אנחנו", 22, 27], "agency_type": "agent", "agentless_reason": null, "position": "subject", "animacy": "human", "morphology": "1pl"}], "agency_predicates": [{"source": ["לצמצם", 35, 40]}], "agents_of_predicates": [{"agent_source": ["אנחנו", 22, 27], "predicate_source": ["לצמצם", 35, 40]}], "stances": [{"confidence_level": "low", "stance_type": "effective", "polarity": "positive", "reference_name": null, "reference_type": null}], "stance_polarity_indications": [], "hedges": [], "quantities": [], "named_entites": [], "this_protocol_anchors": [], "time_expression_ranges": [], "non_valid": false, "sent_text": "אני חושב שגם הממשלה – אנחנו צריכים לצמצם את הריכוזיות הזו, את הכוח של הריכוזיות הזו."}