{"check_worthiness": [{"check_worthiness_score": "worth checking", "claim_type": "other type of claim", "factuality_profile_source": "the_speaker", "factuality_profile_value": "CT+", "start_claim_token": ["ביתר", 0, 4]}, {"check_worthiness_score": "worth checking", "claim_type": "other type of claim", "factuality_profile_source": "the_speaker", "factuality_profile_value": "CT+", "start_claim_token": ["והם", 45, 48]}, {"check_worthiness_score": "worth checking", "claim_type": "other type of claim", "factuality_profile_source": "the_speaker", "factuality_profile_value": "CT+", "start_claim_token": ["בחלק", 78, 82]}], "esp_profiles": [], "agencies": [{"source": ["מוקדים", 25, 31], "agency_type": "agent", "agentless_reason": null, "position": "subject", "animacy": "inanimate", "morphology": "3pl"}, {"source": ["קופות-החולים", 64, 76], "agency_type": "experiencer", "agentless_reason": null, "position": "indirect object", "animacy": "inanimate", "morphology": "3pl"}, {"source": null, "agency_type": "agent-less", "agentless_reason": "nominal sentence", "position": null, "animacy": null, "morphology": null}], "agency_predicates": [{"source": ["פועלים", 18, 24]}, {"source": ["מופעלים", 49, 56]}], "agents_of_predicates": [{"agent_source": ["פועלים", 18, 24], "predicate_source": ["מוקדים", 25, 31]}, {"agent_source": ["קופות-החולים", 64, 76], "predicate_source": ["מופעלים", 49, 56]}], "stances": [{"confidence_level": "mid", "stance_type": "epistemic", "polarity": "positive", "reference_name": null, "reference_type": null}, {"confidence_level": "mid", "stance_type": "epistemic", "polarity": "positive", "reference_name": null, "reference_type": null}, {"confidence_level": "mid", "stance_type": "epistemic", "polarity": "positive", "reference_name": null, "reference_type": null}], "stance_polarity_indications": [], "hedges": [], "quantities": [{"expression": ["יתר", 1, 4], "quantifier_type": "partial", "accuracy": null, "the_whole": null}, {"expression": ["חלק", 79, 82], "quantifier_type": "partial", "accuracy": null, "the_whole": null}], "named_entites": [{"entity_name": ["משרד הבריאות", 111, 123], "entity_type": "ORG"}], "this_protocol_anchors": [], "time_expression_ranges": [], "non_valid": false, "sent_text": "ביתר המקומות בארץ פועלים מוקדים לרפואה דחופה והם מופעלים על-ידי קופות-החולים, בחלק מהמקומות בפריפריה גם בתמיכת משרד הבריאות והרשות המקומית."}