{"check_worthiness": [{"check_worthiness_score": "worth checking", "claim_type": "other type of claim", "factuality_profile_source": "the_speaker", "factuality_profile_value": "CT+", "start_claim_token": ["ברוך", 0, 4]}, {"check_worthiness_score": "worth checking", "claim_type": "quantity in the past or present", "factuality_profile_source": "the_speaker", "factuality_profile_value": "CT+", "start_claim_token": ["וגם", 82, 85]}], "esp_profiles": [], "agencies": [{"source": ["הדמוקרטיה", 37, 46], "agency_type": "agent", "agentless_reason": null, "position": "subject", "animacy": "inanimate", "morphology": "3sg"}, {"source": ["לרוב", 86, 90], "agency_type": "experiencer", "agentless_reason": null, "position": "indirect object", "animacy": "human", "morphology": "3sg"}], "agency_predicates": [{"source": ["יצרה", 47, 51]}, {"source": ["יש", 91, 93]}], "agents_of_predicates": [{"agent_source": ["יצרה", 47, 51], "predicate_source": ["הדמוקרטיה", 37, 46]}, {"agent_source": ["לרוב", 86, 90], "predicate_source": ["יש", 91, 93]}], "stances": [{"confidence_level": "mid", "stance_type": "effective", "polarity": "positive", "reference_name": null, "reference_type": null}, {"confidence_level": "mid", "stance_type": "epistemic", "polarity": "positive", "reference_name": null, "reference_type": null}], "stance_polarity_indications": [], "hedges": [], "quantities": [], "named_entites": [], "this_protocol_anchors": [], "time_expression_ranges": [{"original_time_tokens": ["עידן החדש, בעידן הליברלי", 11, 35], "formatted_begin_date": "to_be_added-None-None None:None", "formatted_end_date": "None-None-None None:None"}], "non_valid": false, "sent_text": "ברוך השם, בעידן החדש, בעידן הליברלי, הדמוקרטיה יצרה שינוי והשתנו פני העולם לטובה, וגם לרוב יש זכויות."}