{"check_worthiness": [{"check_worthiness_score": "not worth checking", "claim_type": "prediction", "factuality_profile_source": "the_speaker", "factuality_profile_value": "CT+", "start_claim_token": ["קודם", 0, 4]}, {"check_worthiness_score": "not worth checking", "claim_type": "personal experience", "factuality_profile_source": "the_speaker", "factuality_profile_value": "CT+", "start_claim_token": ["היות", 36, 40]}, {"check_worthiness_score": "not worth checking", "claim_type": "prediction", "factuality_profile_source": "the_speaker", "factuality_profile_value": "CT+", "start_claim_token": ["נקבל", 96, 100]}, {"check_worthiness_score": "not worth checking", "claim_type": "prediction", "factuality_profile_source": "the_speaker", "factuality_profile_value": "CT+", "start_claim_token": ["כי", 142, 144]}], "esp_profiles": [], "agencies": [{"source": ["נתחיל", 78, 83], "agency_type": "agent", "agentless_reason": null, "position": "embedded_pronoun_subject", "animacy": "human", "morphology": "1pl"}, {"source": ["נקבל", 96, 100], "agency_type": "experiencer", "agentless_reason": null, "position": "embedded_pronoun_subject", "animacy": "human", "morphology": "1pl"}, {"source": null, "agency_type": "agent-less", "agentless_reason": "nominal sentence", "position": null, "animacy": null, "morphology": null}, {"source": null, "agency_type": "agent-less", "agentless_reason": "nominal sentence", "position": null, "animacy": null, "morphology": null}], "agency_predicates": [{"source": ["נתחיל", 78, 83]}, {"source": ["נקבל", 96, 100]}], "agents_of_predicates": [{"agent_source": ["נתחיל", 78, 83], "predicate_source": ["נתחיל", 78, 83]}, {"agent_source": ["נקבל", 96, 100], "predicate_source": ["נקבל", 96, 100]}], "stances": [{"confidence_level": "mid", "stance_type": "epistemic", "polarity": "positive", "reference_name": null, "reference_type": null}, {"confidence_level": "mid", "stance_type": "epistemic", "polarity": "positive", "reference_name": null, "reference_type": null}, {"confidence_level": "mid", "stance_type": "epistemic", "polarity": "positive", "reference_name": null, "reference_type": null}, {"confidence_level": "mid", "stance_type": "epistemic", "polarity": "positive", "reference_name": null, "reference_type": null}], "stance_polarity_indications": [], "hedges": [["אולי", 8, 12], ["קצת", 59, 62]], "quantities": [], "named_entites": [{"entity_name": ["שלומי", 13, 18], "entity_type": "PER"}, {"entity_name": ["המל\"ג", 121, 126], "entity_type": "ORG"}], "this_protocol_anchors": [], "time_expression_ranges": [{"original_time_tokens": ["תיכף", 148, 152], "formatted_begin_date": "None-None-None None:None", "formatted_end_date": "None-None-None None:None"}], "non_valid": false, "sent_text": "קודם כל אולי שלומי, נעשה את זה ככה, היות שהבחינות הוא נושא קצת יותר ממוקד, אז נתחיל עם הבחינות, נקבל תשובות לגבי היערכות המל\"ג לבחינות עכשיו, כי זה תיכף קורה, זה מתחיל בעצם, ואז נדבר על מצב הסטודנטים."}